matflow_formable/__init__.py
matflow_formable/_version.py
matflow_formable/load.py
matflow_formable/main.py
matflow_formable/snippets/build_load_case.py
matflow_formable/snippets/fit_yield_function.py
matflow_formable/snippets/optimise_SC_parameters_LM.py
matflow_formable/snippets/read_tensile_test_CSV.py
matflow_formable-0.1.14.dist-info/LICENSE
matflow_formable-0.1.14.dist-info/METADATA
matflow_formable-0.1.14.dist-info/WHEEL
matflow_formable-0.1.14.dist-info/entry_points.txt
matflow_formable-0.1.14.dist-info/top_level.txt
matflow_formable-0.1.14.dist-info/RECORD
